stack_lab/__init__.py
stack_lab/config.py
stack_lab/core.py
stack_lab/decorators.py
stack_lab/exceptions.py
stack_lab/utils.py
stack_lab-1.0.0.dist-info/licenses/LICENSE
stack_lab-1.0.0.dist-info/METADATA
stack_lab-1.0.0.dist-info/WHEEL
stack_lab-1.0.0.dist-info/top_level.txt
stack_lab-1.0.0.dist-info/RECORD
