Metadata-Version: 2.4
Name: stack-lab
Version: 1.0.0
Summary: A professional and extensible Stack implementation in Python
Author-email: Anbu <your_email@example.com>
License: MIT License
Project-URL: Homepage, https://github.com/anbu/stack-lab
Project-URL: Bug Tracker, https://github.com/anbu/stack-lab/issues
Keywords: stack,data structures,python,algorithms
Classifier: Programming Language :: Python :: 3
Classifier: License :: OSI Approved :: MIT License
Classifier: Operating System :: OS Independent
Classifier: Intended Audience :: Developers
Classifier: Topic :: Software Development :: Libraries
License-File: LICENSE
Dynamic: license-file
